chicken.py
chckn-1.0.1.dist-info/AUTHORS
chckn-1.0.1.dist-info/LICENSE
chckn-1.0.1.dist-info/METADATA
chckn-1.0.1.dist-info/WHEEL
chckn-1.0.1.dist-info/entry_points.txt
chckn-1.0.1.dist-info/top_level.txt
chckn-1.0.1.dist-info/RECORD
