Metadata-Version: 2.1
Name: chckn
Version: 1.0.1
Summary: Chicken chicken chicken chicken 'chicken'. Chicken chicken!
Home-page: https://github.com/ntoll/chckn
Author: Nicholas H.Tollervey
Author-email: ntoll@ntoll.org
License: MIT
Platform: UNKNOWN
Classifier: Development Status :: 5 - Production/Stable
Classifier: Environment :: Console
Classifier: Intended Audience :: Developers
Classifier: Intended Audience :: Education
Classifier: License :: OSI Approved :: MIT License
Classifier: Natural Language :: English
Classifier: Programming Language :: Python :: 3.5
Classifier: Topic :: Education
Classifier: Topic :: Communications
Classifier: Topic :: Software Development :: Internationalization
